tgfs/__init__.py
tgfs/api/__init__.py
tgfs/api/client/__init__.py
tgfs/api/client/api/__init__.py
tgfs/api/client/api/client.py
tgfs/api/client/api/directory.py
tgfs/api/client/api/file.py
tgfs/api/client/api/file_desc.py
tgfs/api/client/api/message/__init__.py
tgfs/api/client/api/message/message_broker.py
tgfs/api/client/api/metadata.py
tgfs/api/client/api/model.py
tgfs/api/client/repository/__init__.py
tgfs/api/client/repository/impl/fd/tg_msg.py
tgfs/api/client/repository/impl/file/__init__.py
tgfs/api/client/repository/impl/file/file_uploader.py
tgfs/api/client/repository/impl/metadata/tg_msg.py
tgfs/api/client/repository/interface.py
tgfs/api/impl/__init__.py
tgfs/api/impl/telethon.py
tgfs/api/interface.py
tgfs/api/ops.py
tgfs/api/types.py
tgfs/config.py
tgfs/errors/__init__.py
tgfs/errors/authentication.py
tgfs/errors/base.py
tgfs/errors/error_code.py
tgfs/errors/path.py
tgfs/errors/telegram.py
tgfs/errors/tgfs.py
tgfs/model/common.py
tgfs/model/directory.py
tgfs/model/file.py
tgfs/model/message.py
tgfs/model/metadata.py
tgfs/server/__init__.py
tgfs/server/webdav/__init__.py
tgfs/server/webdav/cache.py
tgfs/server/webdav/folder.py
tgfs/server/webdav/resource.py
tgfs/utils/logger.py
tgfs/utils/others.py
tgfs-0.1.0.dist-info/LICENSE
tgfs-0.1.0.dist-info/METADATA
tgfs-0.1.0.dist-info/WHEEL
tgfs-0.1.0.dist-info/RECORD
