Metadata-Version: 2.3
Name: tgfs
Version: 0.1.0
Summary: 
Author: WheatCarrier
Author-email: wheatcarrier@gmail.com
Requires-Python: >=3.13,<4.0
Classifier: Programming Language :: Python :: 3
Classifier: Programming Language :: Python :: 3.13
Requires-Dist: fastapi (>=0.115.12,<0.116.0)
Requires-Dist: lru-dict (>=1.3.0,<2.0.0)
Requires-Dist: lxml (>=5.4.0,<6.0.0)
Requires-Dist: poetry-core (>=2.0.0,<3.0.0)
Requires-Dist: pyrate-limiter (>=3.7.0,<4.0.0)
Requires-Dist: pyyaml (>=6.0.2,<7.0.0)
Requires-Dist: telethon (>=1.40.0,<2.0.0)
Requires-Dist: uvicorn (>=0.34.3,<0.35.0)
